bose_request/__init__.py
bose_request/json_validator.py
bose_request/patch_curl_cffi/__init__.py
bose_request/patch_curl_cffi/async_client.py
bose_request/patch_curl_cffi/client.py
bose_request/patch_httpx/__init__.py
bose_request/patch_httpx/client.py
boss_request-0.0.7.dist-info/METADATA
boss_request-0.0.7.dist-info/WHEEL
boss_request-0.0.7.dist-info/top_level.txt
boss_request-0.0.7.dist-info/RECORD
